README.md
setup.py
twitter_auto_upload_image/__init__.py
twitter_auto_upload_image.egg-info/PKG-INFO
twitter_auto_upload_image.egg-info/SOURCES.txt
twitter_auto_upload_image.egg-info/dependency_links.txt
twitter_auto_upload_image.egg-info/requires.txt
twitter_auto_upload_image.egg-info/top_level.txt